uc_logging/__init__.py
uc_logging-0.0.2.dist-info/LICENSE
uc_logging-0.0.2.dist-info/METADATA
uc_logging-0.0.2.dist-info/WHEEL
uc_logging-0.0.2.dist-info/top_level.txt
uc_logging-0.0.2.dist-info/RECORD
