Metadata-Version: 2.1
Name: uc-logging
Version: 0.0.2
Summary: A set of classes and functions that extend the log package.
Home-page: https://github.com/dentist128/uc_logging
Author: Eduard S. Markelov
Author-email: markeloveduard@gmail.com
License: UNKNOWN
Platform: UNKNOWN
Classifier: Programming Language :: Python :: 3
Classifier: License :: OSI Approved :: GNU Affero General Public License v3
Classifier: Operating System :: OS Independent
Requires-Python: >=3.4, <4
